Metadata-Version: 1.1
Name: simple-django-teams
Version: 0.0.6
Summary: Simple Django teams.
Home-page: UNKNOWN
Author: Corey Sterling
Author-email: coreytsterling@gmail.com
License: MIT
Platform: UNKNOWN
Classifier: Development Status :: 4 - Beta
Classifier: License :: OSI Approved :: MIT License
Classifier: Topic :: Scientific/Engineering :: Mathematics
Classifier: Programming Language :: Python :: 3.7
